geocode_sqlite/__init__.py
geocode_sqlite/cli.py
geocode_sqlite/testing.py
geocode_sqlite/utils.py
geocode_sqlite-0.8.2.dist-info/LICENSE
geocode_sqlite-0.8.2.dist-info/METADATA
geocode_sqlite-0.8.2.dist-info/WHEEL
geocode_sqlite-0.8.2.dist-info/entry_points.txt
geocode_sqlite-0.8.2.dist-info/top_level.txt
geocode_sqlite-0.8.2.dist-info/RECORD
