Metadata-Version: 2.1
Name: geocode-sqlite
Version: 0.8.2
Summary: Geocode rows from a SQLite table
Home-page: https://github.com/eyeseast/geocode-sqlite
Author: Chris Amico
License: Apache License, Version 2.0
Project-URL: Issues, https://github.com/eyeseast/geocode-sqlite/issues
Project-URL: CI, https://github.com/eyeseast/geocode-sqlite/actions
Project-URL: Changelog, https://github.com/eyeseast/geocode-sqlite/releases
Platform: UNKNOWN
Requires-Dist: click (>=7.0)
Requires-Dist: sqlite-utils
Requires-Dist: geopy
Requires-Dist: requests
Provides-Extra: test
Requires-Dist: pytest ; extra == 'test'
Requires-Dist: geojson-to-sqlite ; extra == 'test'
